check_project/__init__.py
check_project/__main__.py
check_project/cli.py
check_project/gitproject.py
check_project-0.1.0.dist-info/DESCRIPTION.rst
check_project-0.1.0.dist-info/entry_points.txt
check_project-0.1.0.dist-info/METADATA
check_project-0.1.0.dist-info/metadata.json
check_project-0.1.0.dist-info/pbr.json
check_project-0.1.0.dist-info/RECORD
check_project-0.1.0.dist-info/top_level.txt
check_project-0.1.0.dist-info/WHEEL
