Metadata-Version: 2.0
Name: check-project
Version: 0.1.0
Summary: Check project directories for uncommitted or unpushed work and for files like README and LICENSE.
Home-page: https://github.com/adamwolf/check_project
Author: Adam Wolf
Author-email: adamwolf@feelslikeburning.com
License: GPLv2
Keywords: unpushed uncommitted style
Platform: UNKNOWN
Classifier: Development Status :: 3 - Alpha
Classifier: License :: OSI Approved :: GNU General Public License v2 (GPLv2)
Classifier: Programming Language :: Python :: 2
Classifier: Programming Language :: Python :: 2.7
Classifier: Programming Language :: Python :: 3
Classifier: Environment :: Console
Classifier: Intended Audience :: Developers
